README.md
setup.cfg
setup.py
test/test_advanced_location.py
test/test_assigned_shift.py
test/test_capacity.py
test/test_cargo.py
test/test_cargo_placement.py
test/test_configuration.py
test/test_configurator_api.py
test/test_data_api.py
test/test_data_load_result.py
test/test_data_load_task.py
test/test_delete_filter.py
test/test_demand.py
test/test_fact_demand_cancellation.py
test/test_fact_demand_done.py
test/test_fact_demand_payment.py
test/test_fact_demand_resumed.py
test/test_fact_event_window_changed.py
test/test_fact_job_done.py
test/test_fact_performer_message.py
test/test_fact_photo.py
test/test_fact_trip_progress.py
test/test_fact_trip_status_notice.py
test/test_fact_tripaction_comment_changed.py
test/test_fact_work_started.py
test/test_facts_filter.py
test/test_facts_result.py
test/test_inline_response400.py
test/test_inline_response401.py
test/test_inline_response403.py
test/test_inline_response404.py
test/test_inline_response415.py
test/test_inline_response429.py
test/test_inline_response500.py
test/test_inline_response501.py
test/test_inline_response502.py
test/test_inline_response503.py
test/test_inline_response504.py
test/test_inline_response_default.py
test/test_load_window.py
test/test_location.py
test/test_merchandise_line.py
test/test_monitor_api.py
test/test_order.py
test/test_order_cancellation.py
test/test_orders_filter.py
test/test_orders_result.py
test/test_payment_details.py
test/test_performer_track.py
test/test_performers_filter.py
test/test_photos_filter.py
test/test_possible_event.py
test/test_predict_result_window.py
test/test_predictor_api.py
test/test_predictor_check_result.py
test/test_predictor_insert_task.py
test/test_predictor_result.py
test/test_predictor_task.py
test/test_report_filter.py
test/test_reports_api.py
test/test_run_trips_task.py
test/test_time_window.py
test/test_trace_data.py
test/test_track_point.py
test/test_tracks_result.py
test/test_trip.py
test/test_trip_action.py
test/test_trip_job.py
vrt_ud.egg-info/PKG-INFO
vrt_ud.egg-info/SOURCES.txt
vrt_ud.egg-info/dependency_links.txt
vrt_ud.egg-info/requires.txt
vrt_ud.egg-info/top_level.txt
