Metadata-Version: 1.0
Name: vrt-ud
Version: 3.7.163551
Summary: VeeRoute.UD
Home-page: https://docs.veeroute.com/#/udl/integration/openapi
Author: VeeRoute Support Team
Author-email: support@veeroute.com
License: UNKNOWN
Keywords: OpenAPI,OpenAPI-Generator,VeeRoute.UD
Platform: UNKNOWN
